LICENSE.txt
README.md
setup.py
goldbook/__init__.py
goldbook/admin.py
goldbook/apps.py
goldbook/choices.py
goldbook/models.py
goldbook/views.py
goldbook/wagtail_hooks.py
goldbook.egg-info/PKG-INFO
goldbook.egg-info/SOURCES.txt
goldbook.egg-info/dependency_links.txt
goldbook.egg-info/not-zip-safe
goldbook.egg-info/top_level.txt
goldbook/migrations/0001_initial.py
goldbook/migrations/0002_winetrail_remove_winery_trail_a_part_of_and_more.py
goldbook/migrations/0003_ava_alter_winery_ava.py
goldbook/migrations/0004_winery_food_truck.py
goldbook/migrations/0005_winery_quantity_limit_on_walkin_party_size.py
goldbook/migrations/0006_viewsfromseating_winery_tastingroom_views.py
goldbook/migrations/0007_winery_ceremony_views_and_more.py
goldbook/migrations/0008_alter_winery_address_and_more.py
goldbook/migrations/__init__.py
goldbook/util/__init__.py
goldbook/util/helpers.py