Metadata-Version: 2.1
Name: goldbook
Version: 0.2
Summary: IvyLifeandStyleMedia Gold Book
Home-page: https://github.com/pdbethke/goldbook
Author: siteshell.net
Author-email: pdbethke@siteshell.net
License: LICENSE.txt
Platform: OS Independent
License-File: LICENSE.txt
